pysisso/__init__.py
pysisso/inputs.py
pysisso/jobs.py
pysisso/outputs.py
pysisso/sklearn.py
pysisso/tests/test_inputs.py
pysisso/tests/test_jobs.py
pysisso/tests/test_outputs.py
pysisso/tests/test_sklearn.py
pysisso/tests/test_utils.py
pysisso/tests/test_validators.py
pysisso/utils.py
pysisso/validators.py
pysisso-0.3.2.dist-info/LICENSE.rst
pysisso-0.3.2.dist-info/WHEEL
pysisso-0.3.2.dist-info/METADATA
pysisso-0.3.2.dist-info/RECORD
